<?xml version="1.0" encoding="iso-8859-1"?>
<mosinstall type="template" version="1.0.x">
	<name>ghk01</name>
	<creationDate>23/03/2007</creationDate>
	<author>www.JoomlaDesigns.co.uk</author>
	<copyright>JoomlaDesigns.co.uk</copyright>
	<authorEmail>team@joomladesigns.co.uk</authorEmail>
	<authorUrl>www.joomladesigns.co.uk</authorUrl>
	<version>1.0</version>
	<description>GHK01 template is clean CSS Joomla template developed and released by www.joomladesigns.co.uk This template can only be redistributed by Joomladesigns.co.uk and the copyright link must be visable at the bottom of the design.</description>
	<files>
		<filename>templateDetails.xml</filename>
		<filename>template_thumbnail.png</filename>
		<filename>index.php</filename>
	</files>
	<images>
		<filename>images/main.jpg</filename>
<filename>images/flash.jpg</filename>
<filename>images/grdnt_black.jpg</filename>
<filename>images/dot.gif</filename>
		<filename>images/emailButton.png</filename>
<filename>images/indent1.png</filename>
		<filename>images/indent2.png</filename>
		<filename>images/pdf_button.png</filename>
<filename>images/printButton.png</filename>
<filename>images/spacer.png</filename>
<filename>images/index.html</filename>
	</images>
	<css>
	
		<filename>css/template_css.css</filename>
	</css>
</mosinstall>